django_xhtml2pdf/__init__.py
django_xhtml2pdf/models.py
django_xhtml2pdf/utils.py
django_xhtml2pdf/views.py
django_xhtml2pdf-0.0.4.dist-info/DESCRIPTION.rst
django_xhtml2pdf-0.0.4.dist-info/METADATA
django_xhtml2pdf-0.0.4.dist-info/RECORD
django_xhtml2pdf-0.0.4.dist-info/WHEEL
django_xhtml2pdf-0.0.4.dist-info/metadata.json
django_xhtml2pdf-0.0.4.dist-info/top_level.txt
