Metadata-Version: 1.1
Name: django-xhtml2pdf
Version: 0.0.4
Summary: A Django app to generate pdfs from templates
Home-page: UNKNOWN
Author: Christopher Glass
Author-email: tribaal@gmail.com
License: BSD License
Platform: OS Independent
Classifier: Environment :: Web Environment
Classifier: Framework :: Django
Classifier: Intended Audience :: Developers
Classifier: License :: OSI Approved :: BSD License
Classifier: Operating System :: OS Independent
Classifier: Programming Language :: Python
Classifier: Topic :: Software Development :: Libraries :: Application Frameworks
Classifier: Topic :: Internet :: WWW/HTTP :: Dynamic Content
